{
    "$schema": "https://raw.githubusercontent.com/Cog-Creators/Red-DiscordBot/V3/develop/schema/red_cog.schema.json",
    "author": [
        "Vexed (Vexed#0714)"
    ],
    "description": "Create, comment, labelify and close GitHub issues, with partial PR support.",
    "disabled": true,
    "hidden": true,
    "install_msg": "This cog has been removed in favour of my `ghissues` cog. Please uninstall this one and install that.",
    "min_python_version": [
        3,
        8,
        1
    ],
    "name": "GitHub",
    "short": "Create, comment, labelify and close GitHub issues."
}
